[
    {
        "UpdateStageName": "Download Windows",
        "UpdateSourcePlatform": "Windows",
        "UpdateSource": "SteamCMD",
        "UpdateSourceData": "215350",
        "UpdateSourceArgs": "1250",
        "UnzipUpdateSource": false,
        "OverwriteExistingFiles": false,
        "DeleteAfterExtract": true,
        "OneShot": false
    },
    {
        "UpdateStageName": "Download Linux",
        "UpdateSourcePlatform": "Linux",
        "UpdateSource": "SteamCMD",
        "UpdateSourceData": "215360",
        "UpdateSourceArgs": "1250",
        "UnzipUpdateSource": false,
        "OverwriteExistingFiles": false,
        "DeleteAfterExtract": true,
        "OneShot": false
    }
]